sldl/__init__.py
sldl/_utils/__init__.py
sldl/_utils/models.py
sldl/_utils/video.py
sldl/image/__init__.py
sldl/image/bsrgan.py
sldl/image/denoising.py
sldl/image/realesrgan.py
sldl/image/super_resolution.py
sldl/image/swinir.py
sldl/video/__init__.py
sldl/video/denoising.py
sldl/video/ifrnet.py
sldl/video/super_resolution.py
sldl/video/video_interpolation.py
sldl/video/vrt.py
sldl-0.0.3.dist-info/LICENSE
sldl-0.0.3.dist-info/METADATA
sldl-0.0.3.dist-info/WHEEL
sldl-0.0.3.dist-info/top_level.txt
sldl-0.0.3.dist-info/zip-safe
sldl-0.0.3.dist-info/RECORD
