Metadata-Version: 2.1
Name: sldl
Version: 0.0.3
Summary: Single-line inference of SOTA deep learning models
Home-page: https://github.com/pilot7747/sldl
Author: Nikita Pavlichenko
License: Apache 2.0
Keywords: deep learning,computer vision,super resolution,denoising
Classifier: Development Status :: 3 - Alpha
Classifier: Intended Audience :: Developers
Classifier: Intended Audience :: Science/Research
Classifier: License :: OSI Approved :: Apache Software License
Classifier: Operating System :: OS Independent
Classifier: Programming Language :: Python
Classifier: Programming Language :: Python :: 3
Classifier: Programming Language :: Python :: 3.8
Classifier: Programming Language :: Python :: 3.9
Classifier: Programming Language :: Python :: 3.10
Classifier: Programming Language :: Python :: Implementation :: CPython
Classifier: Topic :: Scientific/Engineering
Classifier: Topic :: Software Development
Classifier: Typing :: Typed
Requires-Python: >=3.8
License-File: LICENSE
Requires-Dist: einops
Requires-Dist: huggingface-hub
Requires-Dist: numpy
Requires-Dist: opencv-python
Requires-Dist: Pillow
Requires-Dist: timm
Requires-Dist: torch (>=1.8.1)
Requires-Dist: tqdm
